django_api_admin/__init__.py
django_api_admin/actions.py
django_api_admin/apps.py
django_api_admin/changelist.py
django_api_admin/checks.py
django_api_admin/decorators.py
django_api_admin/exceptions.py
django_api_admin/filters.py
django_api_admin/hooks.py
django_api_admin/models.py
django_api_admin/openapi.py
django_api_admin/options.py
django_api_admin/pagination.py
django_api_admin/permissions.py
django_api_admin/serializers.py
django_api_admin/sites.py
django_api_admin/admin_views/admin_site_views/__init__.py
django_api_admin/admin_views/admin_site_views/admin_api_root.py
django_api_admin/admin_views/admin_site_views/admin_log.py
django_api_admin/admin_views/admin_site_views/app_index.py
django_api_admin/admin_views/admin_site_views/autocomplete.py
django_api_admin/admin_views/admin_site_views/index.py
django_api_admin/admin_views/admin_site_views/language_catalog.py
django_api_admin/admin_views/admin_site_views/obtain_token.py
django_api_admin/admin_views/admin_site_views/password_change.py
django_api_admin/admin_views/admin_site_views/site_context.py
django_api_admin/admin_views/admin_site_views/token_refresh.py
django_api_admin/admin_views/admin_site_views/user_information.py
django_api_admin/admin_views/admin_site_views/view_on_site.py
django_api_admin/admin_views/model_admin_views/__init__.py
django_api_admin/admin_views/model_admin_views/add.py
django_api_admin/admin_views/model_admin_views/change.py
django_api_admin/admin_views/model_admin_views/changelist.py
django_api_admin/admin_views/model_admin_views/delete.py
django_api_admin/admin_views/model_admin_views/detail.py
django_api_admin/admin_views/model_admin_views/handle_action.py
django_api_admin/admin_views/model_admin_views/history.py
django_api_admin/admin_views/model_admin_views/list.py
django_api_admin/admins/__init__.py
django_api_admin/admins/base_admin.py
django_api_admin/admins/inline_admin.py
django_api_admin/admins/model_admin.py
django_api_admin/constants/__init__.py
django_api_admin-1.2.1.dist-info/LICENSE
django_api_admin-1.2.1.dist-info/METADATA
django_api_admin-1.2.1.dist-info/WHEEL
django_api_admin-1.2.1.dist-info/top_level.txt
django_api_admin-1.2.1.dist-info/RECORD
