Metadata-Version: 2.2
Name: django-api-admin
Version: 1.2.1
Summary: A RESTful API implementation of django.contrib.admin, designed for writing custom frontends.
Author-email: Muhammad Salah <msbizzacc0unt@outlook.com>
License: MIT License
Project-URL: Github, https://github.com/demon-bixia/django-api-admin
Classifier: Programming Language :: Python :: 3
Classifier: License :: OSI Approved :: MIT License
Classifier: Operating System :: OS Independent
License-File: LICENSE
Requires-Dist: django
Requires-Dist: djangorestframework
Requires-Dist: djangorestframework-simplejwt
Requires-Dist: drf-spectacular
Provides-Extra: dev
Requires-Dist: django-cors-headers; extra == "dev"
